
[
    {
        "id":1,
        "img_url":"https://images.pexels.com/photos/2265486/pexels-photo-2265486.jpeg?auto=compress&cs=tinysrgb&w=1260&h=750&dpr=1",
        "title":"Napkin Paper",
        "price":599,
        "rating":4.2
    },
    {
        "id":2,
        "img_url":"https://images.pexels.com/photos/2265486/pexels-photo-2265486.jpeg?auto=compress&cs=tinysrgb&w=1260&h=750&dpr=1",
        "title":"Tissue Paper",
        "price":399,
        "rating":3.3
    },
    {
        "id":3,
        "img_url":"https://images.pexels.com/photos/2265486/pexels-photo-2265486.jpeg?auto=compress&cs=tinysrgb&w=1260&h=750&dpr=1",
        "title":"Kitchen Towel",
        "price":199,
        "rating":4.3
    },
    {
        "id":4,
        "img_url":"https://images.pexels.com/photos/2265486/pexels-photo-2265486.jpeg?auto=compress&cs=tinysrgb&w=1260&h=750&dpr=1",
        "title":"PopUp Napkin",
        "price":799,
        "rating":2.3
    }
    
]